MANIFEST.in
README.md
setup.py
boo/__init__.py
boo/boo.py
boo/test_boo.py
boo/examples/3d_6_0.54_0.dat
boo/examples/AR-Res06A_scan2_t890.xyz
boo/examples/crystal-gel.ipynb
boo/examples/periodic_glass.ipynb
pyboo.egg-info/PKG-INFO
pyboo.egg-info/SOURCES.txt
pyboo.egg-info/dependency_links.txt
pyboo.egg-info/requires.txt
pyboo.egg-info/top_level.txt