Metadata-Version: 1.1
Name: pyboo
Version: 1.0.0
Summary: A Python package to compute bond orientational order parameters
Home-page: https://github.com/MathieuLeocmach/pyboo
Author: Mathieu Leocmach
Author-email: mathieu.leocmach@univ-lyon1.fr
License: GPL
Keywords: structure crystallography glass
Platform: UNKNOWN
Classifier: Development Status :: 5 - Production/Stable
Classifier: Intended Audience :: Science/Research
Classifier: Topic :: Scientific/Engineering :: Chemistry
Classifier: Topic :: Scientific/Engineering :: Physics
Classifier: License :: OSI Approved :: GNU General Public License v3 or later (GPLv3+)
Classifier: Programming Language :: Python :: 2
Classifier: Programming Language :: Python :: 2.7
Classifier: Programming Language :: Python :: 3
Classifier: Programming Language :: Python :: 3.5
